tadaqq/clus/__init__.py
tadaqq/clus/clusterer.py
tadaqq/clus/pmap.py
tadaqq/qq/__init__.py
tadaqq/qq/dist.py
tadaqq/qq/err.py
tadaqq/qq/hist.py
tadaqq/qq/qqe.py
tadaqq/slabel/__init__.py
tadaqq/slabel/slabel.py
tadaqq/slabmer/__init__.py
tadaqq/slabmer/slabmer.py
tadaqq/util/__init__.py
tada_qq-2.3.1.dist-info/LICENSE
tada_qq-2.3.1.dist-info/METADATA
tada_qq-2.3.1.dist-info/WHEEL
tada_qq-2.3.1.dist-info/top_level.txt
tada_qq-2.3.1.dist-info/RECORD
